{
    "AX": {
        "error": 0.010616091255812919,
        "error_type": "SEM",
        "filter_outliers_dict": {
            "filter_outliers": true,
            "iterations": 1,
            "std_devs": 3,
            "use_iqr_filtering": false,
            "use_standard_deviation_filtering": false
        },
        "fit": "average",
        "fn": 40,
        "include_baseline_error": false,
        "n": 40,
        "outlier_excluded": [],
        "reviewed": true,
        "user_excluded": [],
        "value": -0.09000657675787807
    },
    "CDD": {
        "error": 2.3503772595531993e-05,
        "error_type": "SEM",
        "filter_outliers_dict": {
            "filter_outliers": true,
            "iterations": 1,
            "std_devs": 10,
            "use_iqr_filtering": false,
            "use_standard_deviation_filtering": false
        },
        "fit": "average",
        "fn": 40,
        "include_baseline_error": false,
        "n": 40,
        "outlier_excluded": [],
        "reviewed": true,
        "user_excluded": [],
        "value": 0.0001564838945341762
    },
    "H1": {
        "error": 0.006011679879943081,
        "error_type": "SEM",
        "filter_outliers_dict": {
            "filter_outliers": true,
            "iterations": 1,
            "std_devs": 3,
            "use_iqr_filtering": false,
            "use_standard_deviation_filtering": false
        },
        "fit": "average",
        "fn": 40,
        "include_baseline_error": false,
        "n": 40,
        "outlier_excluded": [],
        "reviewed": true,
        "user_excluded": [],
        "value": 0.035565825607045555
    },
    "H2": {
        "error": 0.003344492470327944,
        "error_type": "SEM",
        "filter_outliers_dict": {
            "filter_outliers": true,
            "iterations": 1,
            "std_devs": 3,
            "use_iqr_filtering": false,
            "use_standard_deviation_filtering": false
        },
        "fit": "average",
        "fn": 40,
        "include_baseline_error": false,
        "n": 40,
        "outlier_excluded": [],
        "reviewed": true,
        "user_excluded": [],
        "value": -0.0011774358892580495
    },
    "L1": {
        "error": 0.003958986777780108,
        "error_type": "SEM",
        "filter_outliers_dict": {
            "filter_outliers": true,
            "iterations": 1,
            "std_devs": 3,
            "use_iqr_filtering": false,
            "use_standard_deviation_filtering": false
        },
        "fit": "average",
        "fn": 40,
        "include_baseline_error": false,
        "n": 40,
        "outlier_excluded": [],
        "reviewed": true,
        "user_excluded": [],
        "value": 0.0601117477985099
    },
    "L2": {
        "error": 0.008126259924899095,
        "error_type": "SEM",
        "filter_outliers_dict": {
            "filter_outliers": true,
            "iterations": 1,
            "std_devs": 2,
            "use_iqr_filtering": false,
            "use_standard_deviation_filtering": false
        },
        "fit": "Average",
        "fn": 38,
        "include_baseline_error": false,
        "n": 40,
        "outlier_excluded": [
            32,
            10
        ],
        "reviewed": true,
        "user_excluded": [],
        "value": -0.06329781657673027
    }
}