{
    "AX": {
        "error": 0.007228112512189849,
        "error_type": "SEM",
        "filter_outliers_dict": {
            "filter_outliers": true,
            "iterations": 1,
            "std_devs": 2,
            "use_iqr_filtering": false,
            "use_standard_deviation_filtering": false
        },
        "fit": "Average",
        "fn": 39,
        "include_baseline_error": false,
        "n": 40,
        "outlier_excluded": [
            18
        ],
        "reviewed": true,
        "user_excluded": [],
        "value": -0.07676101676546611
    },
    "CDD": {
        "error": 1.0777888277927652e-05,
        "error_type": "SEM",
        "filter_outliers_dict": {
            "filter_outliers": true,
            "iterations": 1,
            "std_devs": 10,
            "use_iqr_filtering": false,
            "use_standard_deviation_filtering": false
        },
        "fit": "Average",
        "fn": 40,
        "include_baseline_error": false,
        "n": 40,
        "outlier_excluded": [],
        "reviewed": true,
        "user_excluded": [],
        "value": 2.671676229510922e-05
    },
    "H1": {
        "error": 0.006679770303743176,
        "error_type": "SEM",
        "filter_outliers_dict": {
            "filter_outliers": true,
            "iterations": 1,
            "std_devs": 2,
            "use_iqr_filtering": false,
            "use_standard_deviation_filtering": false
        },
        "fit": "Average",
        "fn": 39,
        "include_baseline_error": false,
        "n": 40,
        "outlier_excluded": [
            12
        ],
        "reviewed": true,
        "user_excluded": [],
        "value": 0.019330714471811332
    },
    "H2": {
        "error": 0.002667280489893248,
        "error_type": "SEM",
        "filter_outliers_dict": {
            "filter_outliers": true,
            "iterations": 1,
            "std_devs": 2
        },
        "fit": "average",
        "value": 0.009917242208643295
    },
    "L1": {
        "error": 0.004041351162679041,
        "error_type": "SEM",
        "filter_outliers_dict": {
            "filter_outliers": true,
            "iterations": 1,
            "std_devs": 2,
            "use_iqr_filtering": false,
            "use_standard_deviation_filtering": false
        },
        "fit": "Average",
        "fn": 38,
        "include_baseline_error": false,
        "n": 40,
        "outlier_excluded": [
            0,
            17
        ],
        "reviewed": true,
        "user_excluded": [],
        "value": 0.06469848227540129
    },
    "L2": {
        "error": 0.008259810618099332,
        "error_type": "SEM",
        "filter_outliers_dict": {
            "filter_outliers": true,
            "iterations": 1,
            "std_devs": 2,
            "use_iqr_filtering": false,
            "use_standard_deviation_filtering": false
        },
        "fit": "Average",
        "fn": 40,
        "include_baseline_error": false,
        "n": 40,
        "outlier_excluded": [],
        "reviewed": true,
        "user_excluded": [],
        "value": -0.06723625093945884
    }
}