{
    "AX": {
        "error": 0.007446286550233353,
        "error_type": "SEM",
        "filter_outliers_dict": {
            "filter_outliers": true,
            "iterations": 1,
            "std_devs": 2,
            "use_iqr_filtering": false,
            "use_standard_deviation_filtering": false
        },
        "fit": "Average",
        "fn": 39,
        "include_baseline_error": false,
        "n": 40,
        "outlier_excluded": [
            8
        ],
        "reviewed": true,
        "user_excluded": [],
        "value": -0.03180002715984861
    },
    "CDD": {
        "error": 7.333895694797488e-06,
        "error_type": "SEM",
        "filter_outliers_dict": {
            "filter_outliers": true,
            "iterations": 1,
            "std_devs": 10,
            "use_iqr_filtering": false,
            "use_standard_deviation_filtering": false
        },
        "fit": "Average",
        "fn": 40,
        "include_baseline_error": false,
        "n": 40,
        "outlier_excluded": [],
        "reviewed": true,
        "user_excluded": [],
        "value": 1.5266721311490984e-05
    },
    "H1": {
        "error": 0.006959071834080845,
        "error_type": "SEM",
        "filter_outliers_dict": {
            "filter_outliers": true,
            "iterations": 1,
            "std_devs": 2,
            "use_iqr_filtering": false,
            "use_standard_deviation_filtering": false
        },
        "fit": "Average",
        "fn": 39,
        "include_baseline_error": false,
        "n": 40,
        "outlier_excluded": [
            24
        ],
        "reviewed": true,
        "user_excluded": [],
        "value": -0.004085941258101509
    },
    "H2": {
        "error": 0.0025180380444523296,
        "error_type": "SEM",
        "filter_outliers_dict": {
            "filter_outliers": true,
            "iterations": 1,
            "std_devs": 2
        },
        "fit": "average",
        "value": 0.009248382925235653
    },
    "L1": {
        "error": 0.0036950862169262124,
        "error_type": "SEM",
        "filter_outliers_dict": {
            "filter_outliers": true,
            "iterations": 1,
            "std_devs": 2,
            "use_iqr_filtering": false,
            "use_standard_deviation_filtering": false
        },
        "fit": "Average",
        "fn": 39,
        "include_baseline_error": false,
        "n": 40,
        "outlier_excluded": [
            15
        ],
        "reviewed": true,
        "user_excluded": [],
        "value": 0.0615196794940111
    },
    "L2": {
        "error": 0.00743671516707104,
        "error_type": "SEM",
        "filter_outliers_dict": {
            "filter_outliers": true,
            "iterations": 1,
            "std_devs": 2,
            "use_iqr_filtering": false,
            "use_standard_deviation_filtering": false
        },
        "fit": "Average",
        "fn": 38,
        "include_baseline_error": false,
        "n": 40,
        "outlier_excluded": [
            8,
            36
        ],
        "reviewed": true,
        "user_excluded": [],
        "value": -0.04004866165403081
    }
}