{
    "Ar36": {
        "error": 0.0017270679107830895,
        "error_type": "SEM",
        "filter_outliers_dict": {
            "filter_outliers": true,
            "iterations": 1,
            "std_devs": 2,
            "use_iqr_filtering": false,
            "use_standard_deviation_filtering": false
        },
        "fit": "Linear",
        "fn": 20,
        "include_baseline_error": false,
        "n": 20,
        "outlier_excluded": [],
        "reviewed": true,
        "user_excluded": [],
        "value": 0.01473141356678655
    },
    "Ar37": {
        "error": 0.06676240570881573,
        "error_type": "SEM",
        "filter_outliers_dict": {
            "filter_outliers": true,
            "iterations": 1,
            "std_devs": 2,
            "use_iqr_filtering": false,
            "use_standard_deviation_filtering": false
        },
        "fit": "Linear",
        "fn": 20,
        "include_baseline_error": false,
        "n": 20,
        "outlier_excluded": [],
        "reviewed": true,
        "user_excluded": [],
        "value": -0.03722942380294329
    },
    "Ar38": {
        "error": 0.031310381753896686,
        "error_type": "SEM",
        "filter_outliers_dict": {
            "filter_outliers": true,
            "iterations": 1,
            "std_devs": 2,
            "use_iqr_filtering": false,
            "use_standard_deviation_filtering": false
        },
        "fit": "Linear",
        "fn": 20,
        "include_baseline_error": false,
        "n": 20,
        "outlier_excluded": [],
        "reviewed": true,
        "user_excluded": [],
        "value": 0.18700146228884112
    },
    "Ar39": {
        "error": 0.07061490296563333,
        "error_type": "SEM",
        "filter_outliers_dict": {
            "filter_outliers": true,
            "iterations": 1,
            "std_devs": 2,
            "use_iqr_filtering": false,
            "use_standard_deviation_filtering": false
        },
        "fit": "Linear",
        "fn": 20,
        "include_baseline_error": false,
        "n": 20,
        "outlier_excluded": [],
        "reviewed": true,
        "user_excluded": [],
        "value": 0.2022839596748832
    },
    "Ar40": {
        "error": 0.06005999146964573,
        "error_type": "SEM",
        "filter_outliers_dict": {
            "filter_outliers": true,
            "iterations": 1,
            "std_devs": 2,
            "use_iqr_filtering": false,
            "use_standard_deviation_filtering": false
        },
        "fit": "Linear",
        "fn": 19,
        "include_baseline_error": false,
        "n": 20,
        "outlier_excluded": [
            0
        ],
        "reviewed": true,
        "user_excluded": [],
        "value": 3.1689597416600965
    },
    "Ar41": {
        "error": 0.01604751433779182,
        "error_type": "SEM",
        "filter_outliers_dict": {
            "filter_outliers": true,
            "iterations": 1,
            "std_devs": 2
        },
        "fit": "Average",
        "value": 0.10678626441219696
    }
}