{
    "Ar36": {
        "error": 0.00044355786091075487,
        "error_type": "SEM",
        "filter_outliers_dict": {
            "filter_outliers": true,
            "iterations": 1,
            "std_devs": 2,
            "use_iqr_filtering": false,
            "use_standard_deviation_filtering": false
        },
        "fit": "Linear",
        "fn": 115,
        "include_baseline_error": false,
        "n": 120,
        "outlier_excluded": [
            103,
            18,
            75,
            114,
            7
        ],
        "reviewed": true,
        "user_excluded": [],
        "value": 0.03007095945477736
    },
    "Ar37": {
        "error": 0.010571423040053495,
        "error_type": "SEM",
        "filter_outliers_dict": {
            "filter_outliers": true,
            "iterations": 1,
            "std_devs": 2,
            "use_iqr_filtering": false,
            "use_standard_deviation_filtering": false
        },
        "fit": "Linear",
        "fn": 116,
        "include_baseline_error": false,
        "n": 120,
        "outlier_excluded": [
            25,
            82,
            84,
            30
        ],
        "reviewed": true,
        "user_excluded": [],
        "value": 0.003147256136602865
    },
    "Ar38": {
        "error": 0.005854559708063038,
        "error_type": "SEM",
        "filter_outliers_dict": {
            "filter_outliers": true,
            "iterations": 1,
            "std_devs": 2,
            "use_iqr_filtering": false,
            "use_standard_deviation_filtering": false
        },
        "fit": "Linear",
        "fn": 114,
        "include_baseline_error": false,
        "n": 120,
        "outlier_excluded": [
            0,
            1,
            2,
            42,
            43,
            12
        ],
        "reviewed": true,
        "user_excluded": [],
        "value": 0.11941559463388451
    },
    "Ar39": {
        "error": 0.013426575405018175,
        "error_type": "SEM",
        "filter_outliers_dict": {
            "filter_outliers": true,
            "iterations": 1,
            "std_devs": 2,
            "use_iqr_filtering": false,
            "use_standard_deviation_filtering": false
        },
        "fit": "Linear",
        "fn": 116,
        "include_baseline_error": false,
        "n": 120,
        "outlier_excluded": [
            0,
            16,
            45,
            46
        ],
        "reviewed": true,
        "user_excluded": [],
        "value": 3.360905730073377
    },
    "Ar40": {
        "error": 0.01630904221595365,
        "error_type": "SEM",
        "filter_outliers_dict": {
            "filter_outliers": true,
            "iterations": 1,
            "std_devs": 2,
            "use_iqr_filtering": false,
            "use_standard_deviation_filtering": false
        },
        "fit": "Linear",
        "fn": 115,
        "include_baseline_error": false,
        "n": 120,
        "outlier_excluded": [
            24,
            72,
            96,
            84,
            62
        ],
        "reviewed": true,
        "user_excluded": [],
        "value": 43.33123449134885
    },
    "Ar41": {
        "error": 0.0030559810276012964,
        "error_type": "SEM",
        "filter_outliers_dict": {
            "filter_outliers": true,
            "iterations": 1,
            "std_devs": 2
        },
        "fit": "Average",
        "value": 0.06467461451031876
    }
}